Metadata-Version: 1.1
Name: Vocabulary
Version: 0.0.6
Summary: Module to get meaning, synonym, antonym, part_of_speech, usage_example, pronunciation and hyphenation for a given word
Home-page: https://github.com/prodicus/vocabulary
Author: Tasdik Rahman
Author-email: tasdik95@gmail.com
License: MIT
Download-URL: https://github.com/prodicus/vocabulary/tarball/0.0.6
Keywords: Dictionary,Vocabulary,simple dictionary,pydict,dictionary module
Platform: UNKNOWN
Classifier: Intended Audience :: Developers
Classifier: License :: OSI Approved :: MIT License
Classifier: Natural Language :: English
Classifier: Programming Language :: Python
Classifier: Programming Language :: Python :: 2.7
Classifier: Programming Language :: Python :: 3
Classifier: Programming Language :: Python :: 3.4
